processoptim/__colors__.py
processoptim/__disp__.py
processoptim/__init__.py
processoptim/__main__.py
processoptim/__optim__.py
processoptim/__version__.py
processoptim/config.json
processoptim/equilibrium.py
processoptim/process_schema.json
processoptim/processes.py
processoptim/test.py
processoptim/thermo_properties.py
processoptim/tomato_flowsheet.py
processoptim/data/ethanol_water_equilibrium_1bar.txt
processoptim/data/kineticA.txt
processoptim/data/soybean_hexane_equilibrium.txt
processoptim/membrane/membrane.json
processoptim/membrane/membrane.py
processoptim/membrane/solutes.json
processoptim/pylca/demo1.py
processoptim/pylca/lca.py
processoptim/pylca/uiinv.py
processoptim/pylca/lci/02022e70-bffc-4480-9eac-459f0bbe6e92.json
processoptim/pylca/lci/05821736-211a-40a2-9f63-762548248989.json
processoptim/pylca/lci/0d7ba7b3-7138-41ff-853e-1aaefc48e94a.json
processoptim/pylca/lci/1c463da1-049a-4610-a332-f87712e4aa5f.json
processoptim/pylca/lci/274e1bbe-ea78-45ea-9b11-b4653e2e3114.json
processoptim/pylca/lci/2957be63-2bee-408f-aad2-a31c179876c9.json
processoptim/pylca/lci/310e2d6a-40e9-4d04-939b-113e37f3ce2c.json
processoptim/pylca/lci/3ec5f7af-74ea-477b-8bec-b0db95357fde.json
processoptim/pylca/lci/4434e5de-3828-4c54-bd4a-1689f2c88f99.json
processoptim/pylca/lci/4525eba7-c859-467e-8d64-e572929cffa6.json
processoptim/pylca/lci/458128f3-098e-4c2d-9880-63cbc9a14efb.json
processoptim/pylca/lci/499e5072-95f6-486d-826b-96b240da7668.json
processoptim/pylca/lci/4b314907-c58c-4b8c-869b-463cd67ea3d4.json
processoptim/pylca/lci/4e95cb2a-6e80-4cf6-8b73-d5de1a0de495.json
processoptim/pylca/lci/587d9ca0-74e8-4c68-829c-7c69d767c1d7.json
processoptim/pylca/lci/60f553ff-a385-4b30-bdca-89c10c94b95f.json
processoptim/pylca/lci/626d6f74-5103-4a8b-bf7b-330bee409f30.json
processoptim/pylca/lci/68d69176-e93c-45ec-b753-2240645a61c6.json
processoptim/pylca/lci/69060781-1c83-46d9-8d8b-090f5d85e3e1.json
processoptim/pylca/lci/6e4b8baa-d149-413d-a86d-8d399c0f24bb.json
processoptim-0.3.0.dist-info/LICENSE.txt
processoptim-0.3.0.dist-info/METADATA
processoptim-0.3.0.dist-info/WHEEL
processoptim-0.3.0.dist-info/top_level.txt
processoptim-0.3.0.dist-info/RECORD
